rdr/__init__.py
rdr-0.1.0.dist-info/LICENSE
rdr-0.1.0.dist-info/WHEEL
rdr-0.1.0.dist-info/METADATA
rdr-0.1.0.dist-info/RECORD
