Metadata-Version: 2.1
Name: rdr
Version: 0.1.0
Summary: Research design records
Author: Andrew Stewart
Author-email: andrew.c.stewart@gmail.com
Requires-Python: >=3.8,<4.0
Classifier: Programming Language :: Python :: 3
Classifier: Programming Language :: Python :: 3.10
Classifier: Programming Language :: Python :: 3.8
Classifier: Programming Language :: Python :: 3.9
